Metadata-Version: 1.0
Name: scos-distributions-beta
Version: 0.1
Summary: Gaussian distributions
Home-page: UNKNOWN
Author: scoscot
Author-email: UNKNOWN
License: UNKNOWN
Platform: UNKNOWN
